{
  "friendships": [
    {
      "name": "jj",
      "message": "jj is the best",
      "id": 3
    },
    {
      "name": "ผลประกอบการ",
      "message": "วันนี้ผมทำ delete get post เสร็จแล้วครับ เย่ๆๆๆ",
      "id": 4
    },
    {
      "name": "jirasin",
      "message": "thank you very much 5555",
      "id": 5
    },
    {
      "name": "1234",
      "message": "5678",
      "id": 6
    },
    {
      "name": "บอกตัวเอง",
      "message": "ขอบคุณที่ไม่ยอมแพ้ จงพยายามต่อไป เพื่อครอบครัว",
      "id": 7
    }
  ]
}